src/__init__.py
src/lib.py
src/plugins.py
techdebt-0.1.2.data/scripts/techdebt
techdebt-0.1.2.dist-info/LICENSE
techdebt-0.1.2.dist-info/METADATA
techdebt-0.1.2.dist-info/WHEEL
techdebt-0.1.2.dist-info/top_level.txt
techdebt-0.1.2.dist-info/RECORD
