Metadata-Version: 2.1
Name: techdebt
Version: 0.1.2
Summary: A technical debt tracker package
Home-page: https://github.com/lcetinsoy/tech-debt
Author: Laurent Cetinsoy
Author-email: laurent.cetinsoy@gmail.com
License: UNKNOWN
Platform: UNKNOWN
Classifier: Programming Language :: Python :: 3
Classifier: License :: OSI Approved :: MIT License
Classifier: Operating System :: OS Independent
Requires-Dist: matplotlib
Requires-Dist: pandas
Requires-Dist: PyYAML
